SEKKAYBOT/__init__.py
SEKKAYBOT-0.25.612.dist-info/METADATA
SEKKAYBOT-0.25.612.dist-info/WHEEL
SEKKAYBOT-0.25.612.dist-info/top_level.txt
SEKKAYBOT-0.25.612.dist-info/RECORD
