Metadata-Version: 2.1
Name: SEKKAYBOT
Version: 0.25.612
Summary: Lobby bot.
Home-page: https://www.youtube.com
Author: Sekkay
Classifier: Programming Language :: Python :: 3
Classifier: License :: OSI Approved :: MIT License
Classifier: Operating System :: OS Independent
Requires-Dist: crayons
Requires-Dist: fortnitepy ==3.6.9
Requires-Dist: BenBotAsync
Requires-Dist: FortniteAPIAsync
Requires-Dist: sanic ==22.12.0
Requires-Dist: colorama
Requires-Dist: aiohttp
